supplr/__init__.py
supplr/api.py
supplr/board_id.py
supplr/calibration.py
supplr/config.py
supplr/errors.py
supplr/main.py
supplr/parser.py
supplr/struct.py
supplr-0.1.1.dist-info/entry_points.txt
supplr-0.1.1.dist-info/WHEEL
supplr-0.1.1.dist-info/METADATA
supplr-0.1.1.dist-info/RECORD
