Metadata-Version: 2.1
Name: supplr
Version: 0.1.1
Summary: supplr CLI application for management Marathon board
License: Apache License, Version 2.0
Author: GreenLab
Author-email: greenlab@jinr.ru
Requires-Python: >=3.6,<4.0
Classifier: License :: Other/Proprietary License
Classifier: Programming Language :: Python :: 3
Classifier: Programming Language :: Python :: 3.6
Classifier: Programming Language :: Python :: 3.7
Classifier: Programming Language :: Python :: 3.8
Classifier: Programming Language :: Python :: 3.9
Requires-Dist: click (>=8.0.1)
Requires-Dist: pandas (>=1.3.4)
